{
  "region": "CISO",
  "generated_at": "2026-04-27T00:13:36.574297+00:00",
  "horizon_hours": 24,
  "base_rmse_mw": 428.0,
  "forecasts": [
    {
      "period": "2026-04-27T00:00:00Z",
      "forecast_mw": 21942.3,
      "ci_lower": 21103.4,
      "ci_upper": 22781.2
    },
    {
      "period": "2026-04-27T01:00:00Z",
      "forecast_mw": 22403.0,
      "ci_lower": 21438.3,
      "ci_upper": 23367.7
    },
    {
      "period": "2026-04-27T02:00:00Z",
      "forecast_mw": 23101.4,
      "ci_lower": 22010.9,
      "ci_upper": 24192.0
    },
    {
      "period": "2026-04-27T03:00:00Z",
      "forecast_mw": 24081.4,
      "ci_lower": 22865.0,
      "ci_upper": 25297.7
    },
    {
      "period": "2026-04-27T04:00:00Z",
      "forecast_mw": 24405.9,
      "ci_lower": 23063.7,
      "ci_upper": 25748.1
    },
    {
      "period": "2026-04-27T05:00:00Z",
      "forecast_mw": 24294.1,
      "ci_lower": 22826.0,
      "ci_upper": 25762.1
    },
    {
      "period": "2026-04-27T06:00:00Z",
      "forecast_mw": 23308.8,
      "ci_lower": 21715.0,
      "ci_upper": 24902.7
    },
    {
      "period": "2026-04-27T07:00:00Z",
      "forecast_mw": 22134.3,
      "ci_lower": 20414.6,
      "ci_upper": 23854.0
    },
    {
      "period": "2026-04-27T08:00:00Z",
      "forecast_mw": 21472.8,
      "ci_lower": 19627.3,
      "ci_upper": 23318.4
    },
    {
      "period": "2026-04-27T09:00:00Z",
      "forecast_mw": 20875.5,
      "ci_lower": 18904.2,
      "ci_upper": 22846.9
    },
    {
      "period": "2026-04-27T10:00:00Z",
      "forecast_mw": 20656.8,
      "ci_lower": 18559.6,
      "ci_upper": 22754.0
    },
    {
      "period": "2026-04-27T11:00:00Z",
      "forecast_mw": 20516.0,
      "ci_lower": 18292.9,
      "ci_upper": 22739.0
    },
    {
      "period": "2026-04-27T12:00:00Z",
      "forecast_mw": 20669.6,
      "ci_lower": 18320.7,
      "ci_upper": 23018.4
    },
    {
      "period": "2026-04-27T13:00:00Z",
      "forecast_mw": 21393.3,
      "ci_lower": 18918.6,
      "ci_upper": 23868.0
    },
    {
      "period": "2026-04-27T14:00:00Z",
      "forecast_mw": 22814.4,
      "ci_lower": 20213.9,
      "ci_upper": 25415.0
    },
    {
      "period": "2026-04-27T15:00:00Z",
      "forecast_mw": 24167.8,
      "ci_lower": 21441.4,
      "ci_upper": 26894.2
    },
    {
      "period": "2026-04-27T16:00:00Z",
      "forecast_mw": 25417.8,
      "ci_lower": 22565.6,
      "ci_upper": 28270.0
    },
    {
      "period": "2026-04-27T17:00:00Z",
      "forecast_mw": 26410.2,
      "ci_lower": 23432.1,
      "ci_upper": 29388.2
    },
    {
      "period": "2026-04-27T18:00:00Z",
      "forecast_mw": 27014.9,
      "ci_lower": 23911.0,
      "ci_upper": 30118.7
    },
    {
      "period": "2026-04-27T19:00:00Z",
      "forecast_mw": 27260.1,
      "ci_lower": 24030.4,
      "ci_upper": 30489.8
    },
    {
      "period": "2026-04-27T20:00:00Z",
      "forecast_mw": 27216.0,
      "ci_lower": 23860.5,
      "ci_upper": 30571.6
    },
    {
      "period": "2026-04-27T21:00:00Z",
      "forecast_mw": 27178.7,
      "ci_lower": 23697.4,
      "ci_upper": 30660.1
    },
    {
      "period": "2026-04-27T22:00:00Z",
      "forecast_mw": 27123.1,
      "ci_lower": 23515.9,
      "ci_upper": 30730.3
    },
    {
      "period": "2026-04-27T23:00:00Z",
      "forecast_mw": 26823.4,
      "ci_lower": 23090.4,
      "ci_upper": 30556.4
    }
  ]
}