{
  "region": "CPLE",
  "trained_at": "2026-04-28T12:28:59.950801+00:00",
  "train_samples": 1824,
  "test_samples": 168,
  "train_period": {
    "start": "2026-02-04T12:00:00Z",
    "end": "2026-04-21T11:00:00Z"
  },
  "test_period": {
    "start": "2026-04-21T12:00:00Z",
    "end": "2026-04-28T11:00:00Z"
  },
  "metrics": {
    "mape_pct": 1.24,
    "rmse_mw": 97.1,
    "mae_mw": 76.0,
    "r2": 0.9919
  },
  "feature_importances": {
    "demand_lag_1": 0.7424,
    "demand_lag_2": 0.1925,
    "demand_diff_1": 0.0267,
    "rolling_mean_6": 0.0076,
    "demand_lag_168": 0.0076,
    "hour": 0.0042,
    "demand_lag_24": 0.0038,
    "demand_diff_24": 0.0029,
    "demand_lag_3": 0.0028,
    "rolling_mean_24": 0.0027,
    "month": 0.0019,
    "rolling_mean_168": 0.0016,
    "day_of_week": 0.0009,
    "rolling_std_24": 0.0009,
    "is_weekend": 0.0008,
    "demand_lag_48": 0.0007
  },
  "best_iteration": 259,
  "n_estimators_used": 260,
  "hyperparameters": {
    "n_estimators": 500,
    "max_depth": 6,
    "learning_rate": 0.05,
    "subsample": 0.8,
    "colsample_bytree": 0.8,
    "min_child_weight": 5
  }
}