[
  {
    "period": "2026-04-19T21:00:00Z",
    "actual_mw": 13981.0,
    "predicted_mw": 14124.7,
    "error_mw": -143.7,
    "error_pct": 1.03
  },
  {
    "period": "2026-04-19T22:00:00Z",
    "actual_mw": 14454.0,
    "predicted_mw": 13929.3,
    "error_mw": 524.7,
    "error_pct": 3.63
  },
  {
    "period": "2026-04-19T23:00:00Z",
    "actual_mw": 15331.0,
    "predicted_mw": 15149.6,
    "error_mw": 181.4,
    "error_pct": 1.18
  },
  {
    "period": "2026-04-20T00:00:00Z",
    "actual_mw": 16179.0,
    "predicted_mw": 16126.5,
    "error_mw": 52.5,
    "error_pct": 0.32
  },
  {
    "period": "2026-04-20T01:00:00Z",
    "actual_mw": 16440.0,
    "predicted_mw": 16668.0,
    "error_mw": -228.0,
    "error_pct": 1.39
  },
  {
    "period": "2026-04-20T02:00:00Z",
    "actual_mw": 15937.0,
    "predicted_mw": 16370.7,
    "error_mw": -433.7,
    "error_pct": 2.72
  },
  {
    "period": "2026-04-20T03:00:00Z",
    "actual_mw": 15191.0,
    "predicted_mw": 15189.1,
    "error_mw": 1.9,
    "error_pct": 0.01
  },
  {
    "period": "2026-04-20T04:00:00Z",
    "actual_mw": 14399.0,
    "predicted_mw": 14445.3,
    "error_mw": -46.3,
    "error_pct": 0.32
  },
  {
    "period": "2026-04-20T05:00:00Z",
    "actual_mw": 13840.0,
    "predicted_mw": 13865.4,
    "error_mw": -25.4,
    "error_pct": 0.18
  },
  {
    "period": "2026-04-20T06:00:00Z",
    "actual_mw": 13408.0,
    "predicted_mw": 13502.5,
    "error_mw": -94.5,
    "error_pct": 0.7
  },
  {
    "period": "2026-04-20T07:00:00Z",
    "actual_mw": 13173.0,
    "predicted_mw": 13111.5,
    "error_mw": 61.5,
    "error_pct": 0.47
  },
  {
    "period": "2026-04-20T08:00:00Z",
    "actual_mw": 13135.0,
    "predicted_mw": 13103.9,
    "error_mw": 31.1,
    "error_pct": 0.24
  },
  {
    "period": "2026-04-20T09:00:00Z",
    "actual_mw": 13451.0,
    "predicted_mw": 13245.8,
    "error_mw": 205.2,
    "error_pct": 1.53
  },
  {
    "period": "2026-04-20T10:00:00Z",
    "actual_mw": 14288.0,
    "predicted_mw": 13961.5,
    "error_mw": 326.5,
    "error_pct": 2.28
  },
  {
    "period": "2026-04-20T11:00:00Z",
    "actual_mw": 15491.0,
    "predicted_mw": 15363.4,
    "error_mw": 127.6,
    "error_pct": 0.82
  },
  {
    "period": "2026-04-20T12:00:00Z",
    "actual_mw": 16067.0,
    "predicted_mw": 16060.6,
    "error_mw": 6.4,
    "error_pct": 0.04
  },
  {
    "period": "2026-04-20T13:00:00Z",
    "actual_mw": 15760.0,
    "predicted_mw": 16086.9,
    "error_mw": -326.9,
    "error_pct": 2.07
  },
  {
    "period": "2026-04-20T14:00:00Z",
    "actual_mw": 15226.0,
    "predicted_mw": 15140.1,
    "error_mw": 85.9,
    "error_pct": 0.56
  },
  {
    "period": "2026-04-20T15:00:00Z",
    "actual_mw": 15173.0,
    "predicted_mw": 14756.8,
    "error_mw": 416.2,
    "error_pct": 2.74
  },
  {
    "period": "2026-04-20T16:00:00Z",
    "actual_mw": 14755.0,
    "predicted_mw": 15251.4,
    "error_mw": -496.4,
    "error_pct": 3.36
  },
  {
    "period": "2026-04-20T17:00:00Z",
    "actual_mw": 14499.0,
    "predicted_mw": 14567.3,
    "error_mw": -68.3,
    "error_pct": 0.47
  },
  {
    "period": "2026-04-20T18:00:00Z",
    "actual_mw": 14207.0,
    "predicted_mw": 14437.8,
    "error_mw": -230.8,
    "error_pct": 1.62
  },
  {
    "period": "2026-04-20T19:00:00Z",
    "actual_mw": 13944.0,
    "predicted_mw": 13991.1,
    "error_mw": -47.1,
    "error_pct": 0.34
  },
  {
    "period": "2026-04-20T20:00:00Z",
    "actual_mw": 13955.0,
    "predicted_mw": 13818.3,
    "error_mw": 136.7,
    "error_pct": 0.98
  },
  {
    "period": "2026-04-20T21:00:00Z",
    "actual_mw": 14289.0,
    "predicted_mw": 14249.1,
    "error_mw": 39.9,
    "error_pct": 0.28
  },
  {
    "period": "2026-04-20T22:00:00Z",
    "actual_mw": 15089.0,
    "predicted_mw": 14941.8,
    "error_mw": 147.2,
    "error_pct": 0.98
  },
  {
    "period": "2026-04-20T23:00:00Z",
    "actual_mw": 16141.0,
    "predicted_mw": 15868.6,
    "error_mw": 272.4,
    "error_pct": 1.69
  },
  {
    "period": "2026-04-21T00:00:00Z",
    "actual_mw": 17170.0,
    "predicted_mw": 16913.7,
    "error_mw": 256.3,
    "error_pct": 1.49
  },
  {
    "period": "2026-04-21T01:00:00Z",
    "actual_mw": 17472.0,
    "predicted_mw": 17322.2,
    "error_mw": 149.8,
    "error_pct": 0.86
  },
  {
    "period": "2026-04-21T02:00:00Z",
    "actual_mw": 16893.0,
    "predicted_mw": 17098.0,
    "error_mw": -205.0,
    "error_pct": 1.21
  },
  {
    "period": "2026-04-21T03:00:00Z",
    "actual_mw": 15975.0,
    "predicted_mw": 16158.2,
    "error_mw": -183.2,
    "error_pct": 1.15
  },
  {
    "period": "2026-04-21T04:00:00Z",
    "actual_mw": 15093.0,
    "predicted_mw": 15126.0,
    "error_mw": -33.0,
    "error_pct": 0.22
  },
  {
    "period": "2026-04-21T05:00:00Z",
    "actual_mw": 14503.0,
    "predicted_mw": 14322.8,
    "error_mw": 180.2,
    "error_pct": 1.24
  },
  {
    "period": "2026-04-21T06:00:00Z",
    "actual_mw": 14139.0,
    "predicted_mw": 14099.6,
    "error_mw": 39.4,
    "error_pct": 0.28
  },
  {
    "period": "2026-04-21T07:00:00Z",
    "actual_mw": 13967.0,
    "predicted_mw": 13981.8,
    "error_mw": -14.8,
    "error_pct": 0.11
  },
  {
    "period": "2026-04-21T08:00:00Z",
    "actual_mw": 13930.0,
    "predicted_mw": 14017.4,
    "error_mw": -87.4,
    "error_pct": 0.63
  },
  {
    "period": "2026-04-21T09:00:00Z",
    "actual_mw": 14211.0,
    "predicted_mw": 14089.5,
    "error_mw": 121.5,
    "error_pct": 0.85
  },
  {
    "period": "2026-04-21T10:00:00Z",
    "actual_mw": 15063.0,
    "predicted_mw": 14974.3,
    "error_mw": 88.7,
    "error_pct": 0.59
  },
  {
    "period": "2026-04-21T11:00:00Z",
    "actual_mw": 16186.0,
    "predicted_mw": 15994.2,
    "error_mw": 191.8,
    "error_pct": 1.18
  },
  {
    "period": "2026-04-21T12:00:00Z",
    "actual_mw": 16098.0,
    "predicted_mw": 16743.8,
    "error_mw": -645.8,
    "error_pct": 4.01
  },
  {
    "period": "2026-04-21T13:00:00Z",
    "actual_mw": 15090.0,
    "predicted_mw": 15642.7,
    "error_mw": -552.7,
    "error_pct": 3.66
  },
  {
    "period": "2026-04-21T14:00:00Z",
    "actual_mw": 14293.0,
    "predicted_mw": 14025.7,
    "error_mw": 267.3,
    "error_pct": 1.87
  },
  {
    "period": "2026-04-21T15:00:00Z",
    "actual_mw": 13646.0,
    "predicted_mw": 13632.7,
    "error_mw": 13.3,
    "error_pct": 0.1
  },
  {
    "period": "2026-04-21T16:00:00Z",
    "actual_mw": 13324.0,
    "predicted_mw": 13251.6,
    "error_mw": 72.4,
    "error_pct": 0.54
  },
  {
    "period": "2026-04-21T17:00:00Z",
    "actual_mw": 12994.0,
    "predicted_mw": 13068.6,
    "error_mw": -74.6,
    "error_pct": 0.57
  },
  {
    "period": "2026-04-21T18:00:00Z",
    "actual_mw": 13043.0,
    "predicted_mw": 12674.7,
    "error_mw": 368.3,
    "error_pct": 2.82
  },
  {
    "period": "2026-04-21T19:00:00Z",
    "actual_mw": 13193.0,
    "predicted_mw": 13296.8,
    "error_mw": -103.8,
    "error_pct": 0.79
  },
  {
    "period": "2026-04-21T20:00:00Z",
    "actual_mw": 13684.0,
    "predicted_mw": 13494.1,
    "error_mw": 189.9,
    "error_pct": 1.39
  },
  {
    "period": "2026-04-21T21:00:00Z",
    "actual_mw": 14646.0,
    "predicted_mw": 14717.3,
    "error_mw": -71.3,
    "error_pct": 0.49
  },
  {
    "period": "2026-04-21T22:00:00Z",
    "actual_mw": 15772.0,
    "predicted_mw": 15735.0,
    "error_mw": 37.0,
    "error_pct": 0.23
  },
  {
    "period": "2026-04-21T23:00:00Z",
    "actual_mw": 16553.0,
    "predicted_mw": 16627.5,
    "error_mw": -74.5,
    "error_pct": 0.45
  },
  {
    "period": "2026-04-22T00:00:00Z",
    "actual_mw": 17124.0,
    "predicted_mw": 17069.5,
    "error_mw": 54.5,
    "error_pct": 0.32
  },
  {
    "period": "2026-04-22T01:00:00Z",
    "actual_mw": 17257.0,
    "predicted_mw": 17043.8,
    "error_mw": 213.2,
    "error_pct": 1.24
  },
  {
    "period": "2026-04-22T02:00:00Z",
    "actual_mw": 16656.0,
    "predicted_mw": 16665.4,
    "error_mw": -9.4,
    "error_pct": 0.06
  },
  {
    "period": "2026-04-22T03:00:00Z",
    "actual_mw": 15641.0,
    "predicted_mw": 15714.3,
    "error_mw": -73.3,
    "error_pct": 0.47
  },
  {
    "period": "2026-04-22T04:00:00Z",
    "actual_mw": 14654.0,
    "predicted_mw": 14668.5,
    "error_mw": -14.5,
    "error_pct": 0.1
  },
  {
    "period": "2026-04-22T05:00:00Z",
    "actual_mw": 14019.0,
    "predicted_mw": 13965.6,
    "error_mw": 53.4,
    "error_pct": 0.38
  },
  {
    "period": "2026-04-22T06:00:00Z",
    "actual_mw": 13559.0,
    "predicted_mw": 13700.3,
    "error_mw": -141.3,
    "error_pct": 1.04
  },
  {
    "period": "2026-04-22T07:00:00Z",
    "actual_mw": 13291.0,
    "predicted_mw": 13202.7,
    "error_mw": 88.3,
    "error_pct": 0.66
  },
  {
    "period": "2026-04-22T08:00:00Z",
    "actual_mw": 13202.0,
    "predicted_mw": 13151.1,
    "error_mw": 50.9,
    "error_pct": 0.39
  },
  {
    "period": "2026-04-22T09:00:00Z",
    "actual_mw": 13397.0,
    "predicted_mw": 13286.3,
    "error_mw": 110.7,
    "error_pct": 0.83
  },
  {
    "period": "2026-04-22T10:00:00Z",
    "actual_mw": 14150.0,
    "predicted_mw": 13952.9,
    "error_mw": 197.1,
    "error_pct": 1.39
  },
  {
    "period": "2026-04-22T11:00:00Z",
    "actual_mw": 15383.0,
    "predicted_mw": 15237.4,
    "error_mw": 145.6,
    "error_pct": 0.95
  },
  {
    "period": "2026-04-22T12:00:00Z",
    "actual_mw": 16086.0,
    "predicted_mw": 15890.0,
    "error_mw": 196.0,
    "error_pct": 1.22
  },
  {
    "period": "2026-04-22T13:00:00Z",
    "actual_mw": 15969.0,
    "predicted_mw": 16086.1,
    "error_mw": -117.1,
    "error_pct": 0.73
  },
  {
    "period": "2026-04-22T14:00:00Z",
    "actual_mw": 15651.0,
    "predicted_mw": 15484.1,
    "error_mw": 166.9,
    "error_pct": 1.07
  },
  {
    "period": "2026-04-22T15:00:00Z",
    "actual_mw": 15211.0,
    "predicted_mw": 15156.9,
    "error_mw": 54.1,
    "error_pct": 0.36
  },
  {
    "period": "2026-04-22T16:00:00Z",
    "actual_mw": 14840.0,
    "predicted_mw": 14953.8,
    "error_mw": -113.8,
    "error_pct": 0.77
  },
  {
    "period": "2026-04-22T17:00:00Z",
    "actual_mw": 14601.0,
    "predicted_mw": 14670.5,
    "error_mw": -69.5,
    "error_pct": 0.48
  },
  {
    "period": "2026-04-22T18:00:00Z",
    "actual_mw": 14377.0,
    "predicted_mw": 14483.0,
    "error_mw": -106.0,
    "error_pct": 0.74
  },
  {
    "period": "2026-04-22T19:00:00Z",
    "actual_mw": 14267.0,
    "predicted_mw": 14350.1,
    "error_mw": -83.1,
    "error_pct": 0.58
  },
  {
    "period": "2026-04-22T20:00:00Z",
    "actual_mw": 14377.0,
    "predicted_mw": 14268.4,
    "error_mw": 108.6,
    "error_pct": 0.76
  },
  {
    "period": "2026-04-22T21:00:00Z",
    "actual_mw": 14671.0,
    "predicted_mw": 14940.0,
    "error_mw": -269.0,
    "error_pct": 1.83
  },
  {
    "period": "2026-04-22T22:00:00Z",
    "actual_mw": 15333.0,
    "predicted_mw": 15647.3,
    "error_mw": -314.3,
    "error_pct": 2.05
  },
  {
    "period": "2026-04-22T23:00:00Z",
    "actual_mw": 16053.0,
    "predicted_mw": 16343.2,
    "error_mw": -290.2,
    "error_pct": 1.81
  },
  {
    "period": "2026-04-23T00:00:00Z",
    "actual_mw": 16754.0,
    "predicted_mw": 16817.4,
    "error_mw": -63.4,
    "error_pct": 0.38
  },
  {
    "period": "2026-04-23T01:00:00Z",
    "actual_mw": 16985.0,
    "predicted_mw": 17038.1,
    "error_mw": -53.1,
    "error_pct": 0.31
  },
  {
    "period": "2026-04-23T02:00:00Z",
    "actual_mw": 16381.0,
    "predicted_mw": 16709.2,
    "error_mw": -328.2,
    "error_pct": 2.0
  },
  {
    "period": "2026-04-23T03:00:00Z",
    "actual_mw": 15386.0,
    "predicted_mw": 15455.5,
    "error_mw": -69.5,
    "error_pct": 0.45
  },
  {
    "period": "2026-04-23T04:00:00Z",
    "actual_mw": 14406.0,
    "predicted_mw": 14270.3,
    "error_mw": 135.7,
    "error_pct": 0.94
  },
  {
    "period": "2026-04-23T05:00:00Z",
    "actual_mw": 13766.0,
    "predicted_mw": 13707.4,
    "error_mw": 58.6,
    "error_pct": 0.43
  },
  {
    "period": "2026-04-23T06:00:00Z",
    "actual_mw": 13346.0,
    "predicted_mw": 13475.7,
    "error_mw": -129.7,
    "error_pct": 0.97
  },
  {
    "period": "2026-04-23T07:00:00Z",
    "actual_mw": 13067.0,
    "predicted_mw": 13099.0,
    "error_mw": -32.0,
    "error_pct": 0.25
  },
  {
    "period": "2026-04-23T08:00:00Z",
    "actual_mw": 12981.0,
    "predicted_mw": 13001.4,
    "error_mw": -20.4,
    "error_pct": 0.16
  },
  {
    "period": "2026-04-23T09:00:00Z",
    "actual_mw": 13200.0,
    "predicted_mw": 13116.2,
    "error_mw": 83.8,
    "error_pct": 0.64
  },
  {
    "period": "2026-04-23T10:00:00Z",
    "actual_mw": 14008.0,
    "predicted_mw": 13725.3,
    "error_mw": 282.7,
    "error_pct": 2.02
  },
  {
    "period": "2026-04-23T11:00:00Z",
    "actual_mw": 15146.0,
    "predicted_mw": 15372.6,
    "error_mw": -226.6,
    "error_pct": 1.5
  },
  {
    "period": "2026-04-23T12:00:00Z",
    "actual_mw": 15141.0,
    "predicted_mw": 15781.2,
    "error_mw": -640.2,
    "error_pct": 4.23
  },
  {
    "period": "2026-04-23T13:00:00Z",
    "actual_mw": 14080.0,
    "predicted_mw": 14832.9,
    "error_mw": -752.9,
    "error_pct": 5.35
  },
  {
    "period": "2026-04-23T14:00:00Z",
    "actual_mw": 13179.0,
    "predicted_mw": 13483.5,
    "error_mw": -304.5,
    "error_pct": 2.31
  },
  {
    "period": "2026-04-23T15:00:00Z",
    "actual_mw": 12664.0,
    "predicted_mw": 12773.0,
    "error_mw": -109.0,
    "error_pct": 0.86
  },
  {
    "period": "2026-04-23T16:00:00Z",
    "actual_mw": 12484.0,
    "predicted_mw": 12595.8,
    "error_mw": -111.8,
    "error_pct": 0.9
  },
  {
    "period": "2026-04-23T17:00:00Z",
    "actual_mw": 12350.0,
    "predicted_mw": 12726.7,
    "error_mw": -376.7,
    "error_pct": 3.05
  },
  {
    "period": "2026-04-23T18:00:00Z",
    "actual_mw": 12498.0,
    "predicted_mw": 12956.2,
    "error_mw": -458.2,
    "error_pct": 3.67
  },
  {
    "period": "2026-04-23T19:00:00Z",
    "actual_mw": 12834.0,
    "predicted_mw": 13573.2,
    "error_mw": -739.2,
    "error_pct": 5.76
  },
  {
    "period": "2026-04-23T20:00:00Z",
    "actual_mw": 13080.0,
    "predicted_mw": 14065.0,
    "error_mw": -985.0,
    "error_pct": 7.53
  },
  {
    "period": "2026-04-23T21:00:00Z",
    "actual_mw": 14144.0,
    "predicted_mw": 13998.5,
    "error_mw": 145.5,
    "error_pct": 1.03
  },
  {
    "period": "2026-04-23T22:00:00Z",
    "actual_mw": 15245.0,
    "predicted_mw": 14909.2,
    "error_mw": 335.8,
    "error_pct": 2.2
  },
  {
    "period": "2026-04-23T23:00:00Z",
    "actual_mw": 15869.0,
    "predicted_mw": 16147.6,
    "error_mw": -278.6,
    "error_pct": 1.76
  },
  {
    "period": "2026-04-24T00:00:00Z",
    "actual_mw": 16516.0,
    "predicted_mw": 16176.8,
    "error_mw": 339.2,
    "error_pct": 2.05
  },
  {
    "period": "2026-04-24T01:00:00Z",
    "actual_mw": 16570.0,
    "predicted_mw": 16566.8,
    "error_mw": 3.2,
    "error_pct": 0.02
  },
  {
    "period": "2026-04-24T02:00:00Z",
    "actual_mw": 15928.0,
    "predicted_mw": 16100.0,
    "error_mw": -172.0,
    "error_pct": 1.08
  },
  {
    "period": "2026-04-24T03:00:00Z",
    "actual_mw": 14996.0,
    "predicted_mw": 15127.0,
    "error_mw": -131.0,
    "error_pct": 0.87
  },
  {
    "period": "2026-04-24T04:00:00Z",
    "actual_mw": 14050.0,
    "predicted_mw": 14111.9,
    "error_mw": -61.9,
    "error_pct": 0.44
  },
  {
    "period": "2026-04-24T05:00:00Z",
    "actual_mw": 13354.0,
    "predicted_mw": 13487.9,
    "error_mw": -133.9,
    "error_pct": 1.0
  },
  {
    "period": "2026-04-24T06:00:00Z",
    "actual_mw": 12893.0,
    "predicted_mw": 12984.5,
    "error_mw": -91.5,
    "error_pct": 0.71
  },
  {
    "period": "2026-04-24T07:00:00Z",
    "actual_mw": 12592.0,
    "predicted_mw": 12668.2,
    "error_mw": -76.2,
    "error_pct": 0.6
  },
  {
    "period": "2026-04-24T08:00:00Z",
    "actual_mw": 12439.0,
    "predicted_mw": 12499.8,
    "error_mw": -60.8,
    "error_pct": 0.49
  },
  {
    "period": "2026-04-24T09:00:00Z",
    "actual_mw": 12590.0,
    "predicted_mw": 12522.9,
    "error_mw": 67.1,
    "error_pct": 0.53
  },
  {
    "period": "2026-04-24T10:00:00Z",
    "actual_mw": 13306.0,
    "predicted_mw": 13061.8,
    "error_mw": 244.2,
    "error_pct": 1.83
  },
  {
    "period": "2026-04-24T11:00:00Z",
    "actual_mw": 14376.0,
    "predicted_mw": 14368.1,
    "error_mw": 7.9,
    "error_pct": 0.05
  },
  {
    "period": "2026-04-24T12:00:00Z",
    "actual_mw": 14862.0,
    "predicted_mw": 15300.0,
    "error_mw": -438.0,
    "error_pct": 2.95
  },
  {
    "period": "2026-04-24T13:00:00Z",
    "actual_mw": 14417.0,
    "predicted_mw": 15148.0,
    "error_mw": -731.0,
    "error_pct": 5.07
  },
  {
    "period": "2026-04-24T14:00:00Z",
    "actual_mw": 13626.0,
    "predicted_mw": 14159.8,
    "error_mw": -533.8,
    "error_pct": 3.92
  },
  {
    "period": "2026-04-24T15:00:00Z",
    "actual_mw": 12834.0,
    "predicted_mw": 13237.4,
    "error_mw": -403.4,
    "error_pct": 3.14
  },
  {
    "period": "2026-04-24T16:00:00Z",
    "actual_mw": 12385.0,
    "predicted_mw": 12619.9,
    "error_mw": -234.9,
    "error_pct": 1.9
  },
  {
    "period": "2026-04-24T17:00:00Z",
    "actual_mw": 12126.0,
    "predicted_mw": 12327.8,
    "error_mw": -201.8,
    "error_pct": 1.66
  },
  {
    "period": "2026-04-24T18:00:00Z",
    "actual_mw": 12031.0,
    "predicted_mw": 12210.1,
    "error_mw": -179.1,
    "error_pct": 1.49
  },
  {
    "period": "2026-04-24T19:00:00Z",
    "actual_mw": 12058.0,
    "predicted_mw": 12305.5,
    "error_mw": -247.5,
    "error_pct": 2.05
  },
  {
    "period": "2026-04-24T20:00:00Z",
    "actual_mw": 12323.0,
    "predicted_mw": 12543.2,
    "error_mw": -220.2,
    "error_pct": 1.79
  },
  {
    "period": "2026-04-24T21:00:00Z",
    "actual_mw": 13020.0,
    "predicted_mw": 13071.7,
    "error_mw": -51.7,
    "error_pct": 0.4
  },
  {
    "period": "2026-04-24T22:00:00Z",
    "actual_mw": 14018.0,
    "predicted_mw": 14117.9,
    "error_mw": -99.9,
    "error_pct": 0.71
  },
  {
    "period": "2026-04-24T23:00:00Z",
    "actual_mw": 15099.0,
    "predicted_mw": 15355.8,
    "error_mw": -256.8,
    "error_pct": 1.7
  },
  {
    "period": "2026-04-25T00:00:00Z",
    "actual_mw": 15830.0,
    "predicted_mw": 15440.7,
    "error_mw": 389.3,
    "error_pct": 2.46
  },
  {
    "period": "2026-04-25T01:00:00Z",
    "actual_mw": 16047.0,
    "predicted_mw": 16104.0,
    "error_mw": -57.0,
    "error_pct": 0.36
  },
  {
    "period": "2026-04-25T02:00:00Z",
    "actual_mw": 15622.0,
    "predicted_mw": 15692.3,
    "error_mw": -70.3,
    "error_pct": 0.45
  },
  {
    "period": "2026-04-25T03:00:00Z",
    "actual_mw": 14890.0,
    "predicted_mw": 14949.3,
    "error_mw": -59.3,
    "error_pct": 0.4
  },
  {
    "period": "2026-04-25T04:00:00Z",
    "actual_mw": 14066.0,
    "predicted_mw": 14235.7,
    "error_mw": -169.7,
    "error_pct": 1.21
  },
  {
    "period": "2026-04-25T05:00:00Z",
    "actual_mw": 13421.0,
    "predicted_mw": 13586.8,
    "error_mw": -165.8,
    "error_pct": 1.24
  },
  {
    "period": "2026-04-25T06:00:00Z",
    "actual_mw": 12963.0,
    "predicted_mw": 13033.3,
    "error_mw": -70.3,
    "error_pct": 0.54
  },
  {
    "period": "2026-04-25T07:00:00Z",
    "actual_mw": 12697.0,
    "predicted_mw": 12678.9,
    "error_mw": 18.1,
    "error_pct": 0.14
  },
  {
    "period": "2026-04-25T08:00:00Z",
    "actual_mw": 12564.0,
    "predicted_mw": 12676.5,
    "error_mw": -112.5,
    "error_pct": 0.9
  },
  {
    "period": "2026-04-25T09:00:00Z",
    "actual_mw": 12579.0,
    "predicted_mw": 12566.8,
    "error_mw": 12.2,
    "error_pct": 0.1
  },
  {
    "period": "2026-04-25T10:00:00Z",
    "actual_mw": 12857.0,
    "predicted_mw": 12914.6,
    "error_mw": -57.6,
    "error_pct": 0.45
  },
  {
    "period": "2026-04-25T11:00:00Z",
    "actual_mw": 13162.0,
    "predicted_mw": 13294.6,
    "error_mw": -132.6,
    "error_pct": 1.01
  },
  {
    "period": "2026-04-25T12:00:00Z",
    "actual_mw": 13318.0,
    "predicted_mw": 13416.6,
    "error_mw": -98.6,
    "error_pct": 0.74
  },
  {
    "period": "2026-04-25T13:00:00Z",
    "actual_mw": 13571.0,
    "predicted_mw": 13163.1,
    "error_mw": 407.9,
    "error_pct": 3.01
  },
  {
    "period": "2026-04-25T14:00:00Z",
    "actual_mw": 14097.0,
    "predicted_mw": 13868.3,
    "error_mw": 228.7,
    "error_pct": 1.62
  },
  {
    "period": "2026-04-25T15:00:00Z",
    "actual_mw": 14348.0,
    "predicted_mw": 14754.0,
    "error_mw": -406.0,
    "error_pct": 2.83
  },
  {
    "period": "2026-04-25T16:00:00Z",
    "actual_mw": 14489.0,
    "predicted_mw": 14647.7,
    "error_mw": -158.7,
    "error_pct": 1.1
  },
  {
    "period": "2026-04-25T17:00:00Z",
    "actual_mw": 14456.0,
    "predicted_mw": 14670.3,
    "error_mw": -214.3,
    "error_pct": 1.48
  },
  {
    "period": "2026-04-25T18:00:00Z",
    "actual_mw": 14367.0,
    "predicted_mw": 14517.6,
    "error_mw": -150.6,
    "error_pct": 1.05
  },
  {
    "period": "2026-04-25T19:00:00Z",
    "actual_mw": 14595.0,
    "predicted_mw": 14470.6,
    "error_mw": 124.4,
    "error_pct": 0.85
  },
  {
    "period": "2026-04-25T20:00:00Z",
    "actual_mw": 14980.0,
    "predicted_mw": 14939.9,
    "error_mw": 40.1,
    "error_pct": 0.27
  },
  {
    "period": "2026-04-25T21:00:00Z",
    "actual_mw": 15373.0,
    "predicted_mw": 15256.8,
    "error_mw": 116.2,
    "error_pct": 0.76
  },
  {
    "period": "2026-04-25T22:00:00Z",
    "actual_mw": 15811.0,
    "predicted_mw": 15847.5,
    "error_mw": -36.5,
    "error_pct": 0.23
  },
  {
    "period": "2026-04-25T23:00:00Z",
    "actual_mw": 16092.0,
    "predicted_mw": 16078.9,
    "error_mw": 13.1,
    "error_pct": 0.08
  },
  {
    "period": "2026-04-26T00:00:00Z",
    "actual_mw": 16276.0,
    "predicted_mw": 16293.0,
    "error_mw": -17.0,
    "error_pct": 0.1
  },
  {
    "period": "2026-04-26T01:00:00Z",
    "actual_mw": 16275.0,
    "predicted_mw": 15999.9,
    "error_mw": 275.1,
    "error_pct": 1.69
  },
  {
    "period": "2026-04-26T02:00:00Z",
    "actual_mw": 15845.0,
    "predicted_mw": 15903.3,
    "error_mw": -58.3,
    "error_pct": 0.37
  },
  {
    "period": "2026-04-26T03:00:00Z",
    "actual_mw": 15190.0,
    "predicted_mw": 15233.5,
    "error_mw": -43.5,
    "error_pct": 0.29
  },
  {
    "period": "2026-04-26T04:00:00Z",
    "actual_mw": 14458.0,
    "predicted_mw": 14496.4,
    "error_mw": -38.4,
    "error_pct": 0.27
  },
  {
    "period": "2026-04-26T05:00:00Z",
    "actual_mw": 13842.0,
    "predicted_mw": 13912.1,
    "error_mw": -70.1,
    "error_pct": 0.51
  },
  {
    "period": "2026-04-26T06:00:00Z",
    "actual_mw": 13402.0,
    "predicted_mw": 13479.8,
    "error_mw": -77.8,
    "error_pct": 0.58
  },
  {
    "period": "2026-04-26T07:00:00Z",
    "actual_mw": 13075.0,
    "predicted_mw": 13111.0,
    "error_mw": -36.0,
    "error_pct": 0.28
  },
  {
    "period": "2026-04-26T08:00:00Z",
    "actual_mw": 12912.0,
    "predicted_mw": 12877.2,
    "error_mw": 34.8,
    "error_pct": 0.27
  },
  {
    "period": "2026-04-26T09:00:00Z",
    "actual_mw": 12890.0,
    "predicted_mw": 12900.4,
    "error_mw": -10.4,
    "error_pct": 0.08
  },
  {
    "period": "2026-04-26T10:00:00Z",
    "actual_mw": 13068.0,
    "predicted_mw": 12931.8,
    "error_mw": 136.2,
    "error_pct": 1.04
  },
  {
    "period": "2026-04-26T11:00:00Z",
    "actual_mw": 13260.0,
    "predicted_mw": 13389.9,
    "error_mw": -129.9,
    "error_pct": 0.98
  },
  {
    "period": "2026-04-26T12:00:00Z",
    "actual_mw": 13252.0,
    "predicted_mw": 13620.8,
    "error_mw": -368.8,
    "error_pct": 2.78
  },
  {
    "period": "2026-04-26T13:00:00Z",
    "actual_mw": 13002.0,
    "predicted_mw": 13100.2,
    "error_mw": -98.2,
    "error_pct": 0.76
  },
  {
    "period": "2026-04-26T14:00:00Z",
    "actual_mw": 12601.0,
    "predicted_mw": 12664.4,
    "error_mw": -63.4,
    "error_pct": 0.5
  },
  {
    "period": "2026-04-26T15:00:00Z",
    "actual_mw": 12067.0,
    "predicted_mw": 12203.5,
    "error_mw": -136.5,
    "error_pct": 1.13
  },
  {
    "period": "2026-04-26T16:00:00Z",
    "actual_mw": 11636.0,
    "predicted_mw": 11842.4,
    "error_mw": -206.4,
    "error_pct": 1.77
  },
  {
    "period": "2026-04-26T17:00:00Z",
    "actual_mw": 11292.0,
    "predicted_mw": 11550.3,
    "error_mw": -258.3,
    "error_pct": 2.29
  },
  {
    "period": "2026-04-26T18:00:00Z",
    "actual_mw": 10934.0,
    "predicted_mw": 11350.5,
    "error_mw": -416.5,
    "error_pct": 3.81
  },
  {
    "period": "2026-04-26T19:00:00Z",
    "actual_mw": 10731.0,
    "predicted_mw": 11243.3,
    "error_mw": -512.3,
    "error_pct": 4.77
  },
  {
    "period": "2026-04-26T20:00:00Z",
    "actual_mw": 11798.0,
    "predicted_mw": 11518.7,
    "error_mw": 279.3,
    "error_pct": 2.37
  }
]