{
  "region": "SWPP",
  "generated_at": "2026-04-27T00:13:37.799235+00:00",
  "horizon_hours": 24,
  "base_rmse_mw": 224.6,
  "forecasts": [
    {
      "period": "2026-04-27T00:00:00Z",
      "forecast_mw": 36134.0,
      "ci_lower": 35693.8,
      "ci_upper": 36574.2
    },
    {
      "period": "2026-04-27T01:00:00Z",
      "forecast_mw": 35987.4,
      "ci_lower": 35481.2,
      "ci_upper": 36493.7
    },
    {
      "period": "2026-04-27T02:00:00Z",
      "forecast_mw": 35155.3,
      "ci_lower": 34583.0,
      "ci_upper": 35727.6
    },
    {
      "period": "2026-04-27T03:00:00Z",
      "forecast_mw": 34028.1,
      "ci_lower": 33389.8,
      "ci_upper": 34666.5
    },
    {
      "period": "2026-04-27T04:00:00Z",
      "forecast_mw": 32363.1,
      "ci_lower": 31658.7,
      "ci_upper": 33067.4
    },
    {
      "period": "2026-04-27T05:00:00Z",
      "forecast_mw": 30559.8,
      "ci_lower": 29789.4,
      "ci_upper": 31330.1
    },
    {
      "period": "2026-04-27T06:00:00Z",
      "forecast_mw": 29372.7,
      "ci_lower": 28536.3,
      "ci_upper": 30209.1
    },
    {
      "period": "2026-04-27T07:00:00Z",
      "forecast_mw": 28549.4,
      "ci_lower": 27646.9,
      "ci_upper": 29451.8
    },
    {
      "period": "2026-04-27T08:00:00Z",
      "forecast_mw": 28123.5,
      "ci_lower": 27155.0,
      "ci_upper": 29092.0
    },
    {
      "period": "2026-04-27T09:00:00Z",
      "forecast_mw": 27955.9,
      "ci_lower": 26921.4,
      "ci_upper": 28990.4
    },
    {
      "period": "2026-04-27T10:00:00Z",
      "forecast_mw": 28298.3,
      "ci_lower": 27197.7,
      "ci_upper": 29398.8
    },
    {
      "period": "2026-04-27T11:00:00Z",
      "forecast_mw": 29302.8,
      "ci_lower": 28136.2,
      "ci_upper": 30469.3
    },
    {
      "period": "2026-04-27T12:00:00Z",
      "forecast_mw": 31021.2,
      "ci_lower": 29788.6,
      "ci_upper": 32253.8
    },
    {
      "period": "2026-04-27T13:00:00Z",
      "forecast_mw": 32111.3,
      "ci_lower": 30812.7,
      "ci_upper": 33409.9
    },
    {
      "period": "2026-04-27T14:00:00Z",
      "forecast_mw": 32711.6,
      "ci_lower": 31346.9,
      "ci_upper": 34076.2
    },
    {
      "period": "2026-04-27T15:00:00Z",
      "forecast_mw": 33299.2,
      "ci_lower": 31868.5,
      "ci_upper": 34729.9
    },
    {
      "period": "2026-04-27T16:00:00Z",
      "forecast_mw": 34078.9,
      "ci_lower": 32582.1,
      "ci_upper": 35575.6
    },
    {
      "period": "2026-04-27T17:00:00Z",
      "forecast_mw": 34831.0,
      "ci_lower": 33268.3,
      "ci_upper": 36393.8
    },
    {
      "period": "2026-04-27T18:00:00Z",
      "forecast_mw": 35536.5,
      "ci_lower": 33907.7,
      "ci_upper": 37165.3
    },
    {
      "period": "2026-04-27T19:00:00Z",
      "forecast_mw": 36387.5,
      "ci_lower": 34692.7,
      "ci_upper": 38082.3
    },
    {
      "period": "2026-04-27T20:00:00Z",
      "forecast_mw": 37245.2,
      "ci_lower": 35484.3,
      "ci_upper": 39006.1
    },
    {
      "period": "2026-04-27T21:00:00Z",
      "forecast_mw": 38072.1,
      "ci_lower": 36245.2,
      "ci_upper": 39899.0
    },
    {
      "period": "2026-04-27T22:00:00Z",
      "forecast_mw": 38669.8,
      "ci_lower": 36776.8,
      "ci_upper": 40562.7
    },
    {
      "period": "2026-04-27T23:00:00Z",
      "forecast_mw": 39062.8,
      "ci_lower": 37103.8,
      "ci_upper": 41021.7
    }
  ]
}